loaih/__init__.py
loaih/build.py
loaih/script.py
loaih/version.py
loaih-1.4.0.dist-info/METADATA
loaih-1.4.0.dist-info/WHEEL
loaih-1.4.0.dist-info/entry_points.txt
loaih-1.4.0.dist-info/RECORD
